mahjong_detector-0.0.6.dist-info/METADATA
mahjong_detector-0.0.6.dist-info/WHEEL
mahjong_detector-0.0.6.dist-info/entry_points.txt
mahjong_detector/__init__.py
mahjong_detector/__main__.py
mahjong_detector/model.onnx
mahjong_detector/predict.py
mahjong_detector/preprocess.py
mahjong_detector-0.0.6.dist-info/RECORD
